Metadata-Version: 1.1
Name: cgc1
Version: 0.0.1
Summary: conveniently good containers
Home-page: https://hydra.ecd.space/f/cgc/
Author: Eduard Christian Dumitrescu
Author-email: eduard.c.dumitrescu@gmail.com
License: LGPLv3
Platform: UNKNOWN
Classifier: Programming Language :: Python :: 3 :: Only
